README.md
setup.py
damip/__init__.py
damip/glmcloud.py
damip/oldtimes.py
damip.egg-info/PKG-INFO
damip.egg-info/SOURCES.txt
damip.egg-info/dependency_links.txt
damip.egg-info/requires.txt
damip.egg-info/top_level.txt