Metadata-Version: 2.1
Name: damip
Version: 0.1.6
Summary: Python SDK for Digitopia Advanced Mechanical Intelligence Platform.
Home-page: https://smart-lands.com/damip
Author: kaiwei.li
Author-email: kaiwei.li@smart-lands.com
License: UNKNOWN
Platform: UNKNOWN
Classifier: Development Status :: 3 - Alpha
Classifier: Intended Audience :: Developers
Classifier: Topic :: Software Development :: Build Tools
Classifier: License :: OSI Approved :: MIT License
Classifier: Programming Language :: Python :: 3
Classifier: Programming Language :: Python :: 3.6
Classifier: Programming Language :: Python :: 3.7
Classifier: Programming Language :: Python :: 3.8
Classifier: Programming Language :: Python :: 3.9
Requires-Python: >=3.6
